{
  "project_info": {
    "project_number": "495850984657",
    "project_id": "chatapp-623c4",
    "storage_bucket": "chatapp-623c4.appspot.com"
  },
  "client": [
    {
      "client_info": {
        "mobilesdk_app_id": "1:495850984657:android:b66f84949ad6f7606a61f0",
        "android_client_info": {
          "package_name": "com.example.chat_app"
        }
      },
      "oauth_client": [
        {
          "client_id": "495850984657-dgjlrkjs40n4ph41v6cfn1ocfc9pr3dt.apps.googleusercontent.com",
          "client_type": 3
        }
      ],
      "api_key": [
        {
          "current_key": "AIzaSyBI8XIPENqX0OMve-MhkG8UqO82KCWJ8sc"
        }
      ],
      "services": {
        "appinvite_service": {
          "other_platform_oauth_client": [
            {
              "client_id": "495850984657-dgjlrkjs40n4ph41v6cfn1ocfc9pr3dt.apps.googleusercontent.com",
              "client_type": 3
            }
          ]
        }
      }
    }
  ],
  "configuration_version": "1"
}